xatlas.cpython-38-x86_64-linux-gnu.so
xatlas.libs/libgcc_s-2298274a.so.1
xatlas.libs/libstdc++-08d5c7eb.so.6.0.33
xatlas-0.0.10.dist-info/METADATA
xatlas-0.0.10.dist-info/WHEEL
xatlas-0.0.10.dist-info/RECORD
xatlas-0.0.10.dist-info/licenses/LICENSE
