Metadata-Version: 2.1
Name: xatlas
Version: 0.0.10
Summary: Python bindings for xatlas
Author-Email: Markus Worchel <m.worchel@campus.tu-berlin.de>
License: MIT License
Project-URL: Homepage, https://github.com/mworchel/xatlas-python
Requires-Python: >=3.8
Provides-Extra: test
Requires-Dist: numpy; extra == "test"
Requires-Dist: pytest; extra == "test"
Requires-Dist: scipy; extra == "test"
Requires-Dist: trimesh; extra == "test"
